fumi/__init__.py
fumi/deployer.py
fumi/launcher.py
fumi/messages.py
fumi/util.py
fumi/deployments/__init__.py
fumi/deployments/git.py
fumi/deployments/local.py
fumi/deployments/prepare.py
fumi/locale/es/LC_MESSAGES/fumi.mo
fumi-0.4.0.dist-info/DESCRIPTION.rst
fumi-0.4.0.dist-info/METADATA
fumi-0.4.0.dist-info/RECORD
fumi-0.4.0.dist-info/WHEEL
fumi-0.4.0.dist-info/entry_points.txt
fumi-0.4.0.dist-info/metadata.json
fumi-0.4.0.dist-info/pbr.json
fumi-0.4.0.dist-info/top_level.txt
