Metadata-Version: 2.0
Name: fumi
Version: 0.4.0
Summary: A small and (hopefully) simple deployment tool
Home-page: https://github.com/rmed/fumi
Author: Rafael Medina García
Author-email: rafamedgar@gmail.com
License: MIT
Keywords: fumi deploy git remote ssh
Platform: UNKNOWN
Classifier: Development Status :: 4 - Beta
Classifier: Environment :: Console
Classifier: Intended Audience :: Developers
Classifier: Topic :: Software Development
Classifier: Topic :: Utilities
Classifier: License :: OSI Approved :: MIT License
Classifier: Programming Language :: Python :: 2
Classifier: Programming Language :: Python :: 2.7
Classifier: Programming Language :: Python :: 3
Classifier: Programming Language :: Python :: 3.4
Classifier: Programming Language :: Python :: 3.5
Requires-Dist: blessings (==1.6)
Requires-Dist: paramiko (==2.0.2)
Requires-Dist: pyyaml (==3.12)
Requires-Dist: scp (==0.10.2)
Requires-Dist: six (==1.10.0)
